seira_craft/__init__.py
seira_craft/crafter.py
seira_craft/default.py
seira_craft/seira.py
seira_craft-0.0.5.dist-info/LICENSE
seira_craft-0.0.5.dist-info/METADATA
seira_craft-0.0.5.dist-info/WHEEL
seira_craft-0.0.5.dist-info/RECORD
