Metadata-Version: 2.1
Name: seira-craft
Version: 0.0.5
Summary: A python package to help craft and manipulate sequences.
Home-page: https://github.com/gedemagt/seira-craft
License: MIT
Keywords: sequence,interval
Author: Jesper Halkjær Jensen
Author-email: mail@jeshj.com
Requires-Python: >=3.7,<4.0
Classifier: License :: OSI Approved :: MIT License
Classifier: Programming Language :: Python :: 3
Classifier: Programming Language :: Python :: 3.7
Classifier: Programming Language :: Python :: 3.8
Classifier: Programming Language :: Python :: 3.9
Classifier: Programming Language :: Python :: 3.10
Classifier: Programming Language :: Python :: 3.11
Project-URL: Repository, https://github.com/gedemagt/seira-craft
